SpinWaveToolkit/__init__.py
SpinWaveToolkit/helpers.py
SpinWaveToolkit/bls/BLSmodel.py
SpinWaveToolkit/bls/__init__.py
SpinWaveToolkit/bls/greenAndFresnel.py
SpinWaveToolkit/bls/core/_class_ObjectiveLens.py
SpinWaveToolkit/core/_class_BulkPolariton.py
SpinWaveToolkit/core/_class_DoubleLayerNumeric.py
SpinWaveToolkit/core/_class_MacrospinEquilibrium.py
SpinWaveToolkit/core/_class_Material.py
SpinWaveToolkit/core/_class_SingleLayer.py
SpinWaveToolkit/core/_class_SingleLayerNumeric.py
SpinWaveToolkit/core/_class_SingleLayerSCcoupled.py
spinwavetoolkit-1.2.0.dist-info/licenses/LICENSE
spinwavetoolkit-1.2.0.dist-info/METADATA
spinwavetoolkit-1.2.0.dist-info/WHEEL
spinwavetoolkit-1.2.0.dist-info/top_level.txt
spinwavetoolkit-1.2.0.dist-info/RECORD
