Metadata-Version: 2.4
Name: SpinWaveToolkit
Version: 1.2.0
Summary: Set of tools useful in spin wave research.
Author-email: Ondřej Wojewoda <ondrej.wojewoda@ceitec.vutbr.cz>
Maintainer-email: Ondřej Wojewoda <ondrej.wojewoda@ceitec.vutbr.cz>, Jan Klíma <jan.klima4@vutbr.cz>, Dominik Pavelka <dominik.pavelka@vutbr.cz>, Michal Urbánek <michal.urbanek@ceitec.vutbr.cz>
Project-URL: Homepage, https://github.com/CEITECmagnonics/SpinWaveToolkit
Project-URL: Documentation, https://ceitecmagnonics.github.io/SpinWaveToolkit/stable/index.html
Project-URL: Bug Reports, https://github.com/CEITECmagnonics/SpinWaveToolkit/issues
Project-URL: Forum, https://github.com/CEITECmagnonics/SpinWaveToolkit/discussions
Project-URL: Release Notes, https://ceitecmagnonics.github.io/SpinWaveToolkit/stable/release_notes.html
Keywords: magnetism,physics,analytical,magnonic,spin-wave
Classifier: Development Status :: 5 - Production/Stable
Classifier: Intended Audience :: Science/Research
Classifier: Intended Audience :: Education
Classifier: Intended Audience :: Developers
Classifier: Topic :: Scientific/Engineering :: Physics
Classifier: Programming Language :: Python :: 3
Classifier: Programming Language :: Python :: 3.7
Classifier: Programming Language :: Python :: 3.8
Classifier: Programming Language :: Python :: 3.9
Classifier: Programming Language :: Python :: 3.10
Classifier: Programming Language :: Python :: 3.11
Classifier: Programming Language :: Python :: 3.12
Classifier: Programming Language :: Python :: 3.13
Classifier: Programming Language :: Python :: 3 :: Only
Requires-Python: >=3.7
License-File: LICENSE
Requires-Dist: numpy>1.20
Requires-Dist: scipy>1.8
Requires-Dist: tqdm>4.66
Provides-Extra: dev
Requires-Dist: black; extra == "dev"
Requires-Dist: pylint; extra == "dev"
Requires-Dist: pytest; extra == "dev"
Requires-Dist: matplotlib; extra == "dev"
Provides-Extra: dev-doc
Requires-Dist: black; extra == "dev-doc"
Requires-Dist: pylint; extra == "dev-doc"
Requires-Dist: pytest; extra == "dev-doc"
Requires-Dist: matplotlib; extra == "dev-doc"
Requires-Dist: sphinx; extra == "dev-doc"
Requires-Dist: pydata-sphinx-theme==0.16.0; extra == "dev-doc"
Requires-Dist: numpydoc; extra == "dev-doc"
Requires-Dist: nbsphinx<=0.9.6; extra == "dev-doc"
Requires-Dist: pypandoc; extra == "dev-doc"
Requires-Dist: sphinx-design; extra == "dev-doc"
Requires-Dist: sphinx-gallery; extra == "dev-doc"
Requires-Dist: ipython; extra == "dev-doc"
Requires-Dist: sphinx-toolbox; extra == "dev-doc"
Requires-Dist: sphinx-copybutton; extra == "dev-doc"
Provides-Extra: deploy
Requires-Dist: sphinx; extra == "deploy"
Requires-Dist: pydata-sphinx-theme==0.16.0; extra == "deploy"
Requires-Dist: numpydoc; extra == "deploy"
Requires-Dist: nbsphinx<=0.9.6; extra == "deploy"
Requires-Dist: pypandoc; extra == "deploy"
Requires-Dist: sphinx-design; extra == "deploy"
Requires-Dist: sphinx-gallery; extra == "deploy"
Requires-Dist: ipython; extra == "deploy"
Requires-Dist: sphinx-toolbox; extra == "deploy"
Requires-Dist: sphinx-copybutton; extra == "deploy"
Provides-Extra: test
Requires-Dist: pytest; extra == "test"
Dynamic: license-file
